[
  {
    "id": "岩手-003",
    "name": "盛岡どんぱ",
    "date": "2025-09-06",
    "area": "東北",
    "prefecture": "岩手県",
    "lat": 39.728694,
    "lng": 141.145525,
    "scale": 10000,
    "url": null
  },
  {
    "id": "茨城-019",
    "name": "rockin'star Carnival(ロッキンスター・カーニバル)",
    "date": "2025-10-04",
    "area": "関東",
    "prefecture": "茨城県",
    "lat": 36.402528,
    "lng": 140.594347,
    "scale": 20000,
    "url": null
  },
  {
    "id": "茨城-020",
    "name": "第2回 おみたま花火大会",
    "date": "2025-10-04",
    "area": "関東",
    "prefecture": "茨城県",
    "lat": 36.085122,
    "lng": 140.19753,
    "scale": 8000,
    "url": null
  },
  {
    "id": "茨城-022",
    "name": "第47回 水郷潮来花火大会",
    "date": "2025-10-18",
    "area": "関東",
    "prefecture": "茨城県",
    "lat": 35.947,
    "lng": 140.556,
    "scale": 2000,
    "url": null
  },
  {
    "id": "茨城-023",
    "name": "サンセットフェスタIN天王崎2025 なめがたの湖上花火大会",
    "date": "2025-10-25",
    "area": "関東",
    "prefecture": "茨城県",
    "lat": 35.990245,
    "lng": 140.4733,
    "scale": 5000,
    "url": null
  },
  {
    "id": "茨城-025",
    "name": "第50回 神栖花火大会",
    "date": "2025-11-22",
    "area": "関東",
    "prefecture": "茨城県",
    "lat": 35.866,
    "lng": 140.132,
    "scale": 3000,
    "url": null
  },
  {
    "id": "栃木-017",
    "name": "第3回 渡良瀬遊水地花火大会",
    "date": "2025-10-25",
    "area": "関東",
    "prefecture": "栃木県",
    "lat": 36.256714,
    "lng": 139.657453,
    "scale": 10000,
    "url": null
  },
  {
    "id": "栃木-018",
    "name": "=さくら市市制20周年=さくら市きれつ川花火大会2025",
    "date": "2025-11-08",
    "area": "関東",
    "prefecture": "栃木県",
    "lat": 36.714324,
    "lng": 140.030943,
    "scale": 6000,
    "url": null
  },
  {
    "id": "群馬-015",
    "name": "榛名ふるさと祭り 商工祭花火大会",
    "date": "2025-08-15",
    "area": "関東",
    "prefecture": "群馬県",
    "lat": 36.382457,
    "lng": 138.88654,
    "scale": 3000,
    "url": null
  },
  {
    "id": "群馬-016",
    "name": "第5回 桐生市花火大会",
    "date": "2025-09-28",
    "area": "関東",
    "prefecture": "群馬県",
    "lat": 36.394,
    "lng": 139.337674,
    "scale": 3000,
    "url": null
  },
  {
    "id": "群馬-017",
    "name": "刀水橋花火大会",
    "date": "2025-11-01",
    "area": "関東",
    "prefecture": "群馬県",
    "lat": 35.866,
    "lng": 140.132,
    "scale": 7500,
    "url": null
  },
  {
    "id": "埼玉-022",
    "name": "第26回 ひがしまつやま花火大会",
    "date": "2025-08-23",
    "area": "関東",
    "prefecture": "埼玉県",
    "lat": 36.009342,
    "lng": 139.4027,
    "scale": 5000,
    "url": null
  },
  {
    "id": "埼玉-024",
    "name": "西武園ゆうえんち大火祭り",
    "date": "2025-07-19",
    "area": "関東",
    "prefecture": "埼玉県",
    "lat": 35.769024,
    "lng": 139.442654,
    "scale": null,
    "url": null
  },
  {
    "id": "埼玉-025",
    "name": "第5回 川口花火大会",
    "date": "2025-10-18",
    "area": "関東",
    "prefecture": "埼玉県",
    "lat": 36.13646,
    "lng": 139.381126,
    "scale": 11100,
    "url": null
  },
  {
    "id": "埼玉-026",
    "name": "第11回 浦和美園まつり＆花火大会",
    "date": "2025-10-19",
    "area": "関東",
    "prefecture": "埼玉県",
    "lat": 35.862,
    "lng": 139.646,
    "scale": 11,
    "url": null
  },
  {
    "id": "埼玉-029",
    "name": "秩父夜祭 花火大会",
    "date": "2025-12-03",
    "area": "関東",
    "prefecture": "埼玉県",
    "lat": 35.992,
    "lng": 139.086,
    "scale": 5000,
    "url": null
  },
  {
    "id": "千葉-029",
    "name": "君津市民花火大会",
    "date": "2025-09-27",
    "area": "関東",
    "prefecture": "千葉県",
    "lat": 35.331,
    "lng": 139.9,
    "scale": 2500,
    "url": null
  },
  {
    "id": "千葉-030",
    "name": "令和7年度  流山花火大会",
    "date": "2025-10-04",
    "area": "関東",
    "prefecture": "千葉県",
    "lat": 35.738,
    "lng": 139.912,
    "scale": 8000,
    "url": null
  },
  {
    "id": "千葉-031",
    "name": "SKY ORCHESTRA in SUNSET BEACH PARK INAGE(スカイオーケストラ イン サンセットビーチパーク稲毛)【2025年中止】",
    "date": "2025-10-18",
    "area": "関東",
    "prefecture": "千葉県",
    "lat": 35.621366,
    "lng": 140.059477,
    "scale": 2025,
    "url": null
  },
  {
    "id": "千葉-033",
    "name": "栄町町制70周年記念事業 SAKAEリバーサイド・フェスティバル",
    "date": "2025-10-25",
    "area": "関東",
    "prefecture": "千葉県",
    "lat": 35.866,
    "lng": 140.132,
    "scale": 2000,
    "url": null
  },
  {
    "id": "千葉-035",
    "name": "King＆Princeとうちあげ花火",
    "date": "2025-11-15",
    "area": "関東",
    "prefecture": "千葉県",
    "lat": 35.645234,
    "lng": 140.03086,
    "scale": null,
    "url": null
  },
  {
    "id": "千葉-036",
    "name": "千葉Xmas芸術花火2025",
    "date": "2025-11-24",
    "area": "関東",
    "prefecture": "千葉県",
    "lat": 35.643185,
    "lng": 140.041932,
    "scale": 13000,
    "url": null
  },
  {
    "id": "千葉-037",
    "name": "桜華絢爛花火2025",
    "date": "2025-12-13",
    "area": "関東",
    "prefecture": "千葉県",
    "lat": 35.59302,
    "lng": 140.117845,
    "scale": 2025,
    "url": null
  },
  {
    "id": "東京-017",
    "name": "2025 神宮外苑花火大会",
    "date": "2025-08-16",
    "area": "関東",
    "prefecture": "東京都",
    "lat": 35.676,
    "lng": 139.718,
    "scale": 10000,
    "url": null
  },
  {
    "id": "東京-021",
    "name": "お台場レインボー花火2025",
    "date": "2025-12-06",
    "area": "関東",
    "prefecture": "東京都",
    "lat": 35.631,
    "lng": 139.777,
    "scale": 1300,
    "url": null
  },
  {
    "id": "神奈-022",
    "name": "みなとみらいスマートフェスティバル 2025",
    "date": "2025-08-04",
    "area": "関東",
    "prefecture": "神奈川県",
    "lat": 35.453,
    "lng": 139.638,
    "scale": 20000,
    "url": null
  },
  {
    "id": "神奈-025",
    "name": "第39回 宮ヶ瀬ふるさとまつり",
    "date": "2025-08-13",
    "area": "関東",
    "prefecture": "神奈川県",
    "lat": 35.522379,
    "lng": 139.226946,
    "scale": null,
    "url": null
  },
  {
    "id": "神奈-027",
    "name": "第78回 秦野たばこ祭",
    "date": "2025-09-28",
    "area": "関東",
    "prefecture": "神奈川県",
    "lat": 35.373971,
    "lng": 139.223035,
    "scale": 78,
    "url": null
  },
  {
    "id": "神奈-029",
    "name": "ふじさわ江の島花火大会",
    "date": "2025-10-18",
    "area": "関東",
    "prefecture": "神奈川県",
    "lat": 35.311635,
    "lng": 139.478256,
    "scale": 1000,
    "url": null
  },
  {
    "id": "神奈-030",
    "name": "第9回つくい湖湖上祭",
    "date": "2025-11-16",
    "area": "関東",
    "prefecture": "神奈川県",
    "lat": 35.588613,
    "lng": 139.284373,
    "scale": 2000,
    "url": null
  },
  {
    "id": "神奈-031",
    "name": "三崎城ヶ島花火大会",
    "date": "2025-11-23",
    "area": "関東",
    "prefecture": "神奈川県",
    "lat": 35.140907,
    "lng": 139.61637,
    "scale": 1200,
    "url": null
  },
  {
    "id": "神奈-032",
    "name": "さがみ湖イルミリオン カウントダウン2026",
    "date": "2025-12-31",
    "area": "関東",
    "prefecture": "神奈川県",
    "lat": 35.605397,
    "lng": 139.207563,
    "scale": null,
    "url": null
  },
  {
    "id": "神奈-033",
    "name": "よこすかカウントダウン2026",
    "date": "2025-12-31",
    "area": "関東",
    "prefecture": "神奈川県",
    "lat": 35.283428,
    "lng": 139.658978,
    "scale": 500,
    "url": null
  },
  {
    "id": "岐阜-004",
    "name": "第37回 おがせ池夏まつり花火大会",
    "date": "2025-07-19",
    "area": "中部",
    "prefecture": "岐阜県",
    "lat": 35.412061,
    "lng": 136.910424,
    "scale": 1000,
    "url": null
  },
  {
    "id": "奈良-002",
    "name": "航空自衛隊奈良基地 花火打上(平城山納涼会)",
    "date": "2025-09-06",
    "area": "近畿",
    "prefecture": "奈良県",
    "lat": 34.700263,
    "lng": 135.806611,
    "scale": 400,
    "url": null
  },
  {
    "id": "奈良-003",
    "name": "令和7年 第17回 平維盛の大祭",
    "date": "2025-07-26",
    "area": "近畿",
    "prefecture": "奈良県",
    "lat": 34.11341,
    "lng": 135.644705,
    "scale": 3000,
    "url": null
  },
  {
    "id": "鳥取-004",
    "name": "第80回 みなと祭花火大会",
    "date": "2025-07-27",
    "area": "中国四国",
    "prefecture": "鳥取県",
    "lat": 35.43,
    "lng": 133.33,
    "scale": 2000,
    "url": null
  },
  {
    "id": "鳥取-005",
    "name": "とっとり花火回廊2025",
    "date": "2025-07-12",
    "area": "中国四国",
    "prefecture": "鳥取県",
    "lat": 35.347801,
    "lng": 133.422989,
    "scale": 15000,
    "url": null
  },
  {
    "id": "島根-003",
    "name": "第20回 出雲神話まつり 花火大会",
    "date": "2025-08-23",
    "area": "中国四国",
    "prefecture": "島根県",
    "lat": 35.37,
    "lng": 132.76,
    "scale": 20,
    "url": null
  }
]